mydomuk/__init__.py
mydomuk/dbalance/__init__.py
mydomuk/dbalance/__main__.py
mydomuk/dbalance/constants.py
mydomuk/dbalance/logger.py
mydomuk/dbalance/mydocker/__init__.py
mydomuk/dbalance/mydocker/container.py
mydomuk/dbalance/mydocker/node.py
mydomuk/dbalance/mydocker/service.py
mydomuk/dbalance/mydocker/swarm.py
mydomuk/dbalance/mydocker/task.py
mydomuk/dbalance/mydocker/utils.py
mydomuk.dbalance-1.0.1.dist-info/METADATA
mydomuk.dbalance-1.0.1.dist-info/WHEEL
mydomuk.dbalance-1.0.1.dist-info/top_level.txt
mydomuk.dbalance-1.0.1.dist-info/RECORD
