Metadata-Version: 2.1
Name: mydomuk.dbalance
Version: 1.0.1
Summary: Docker Balance Tool to help moving Services in a Swarm between Nodes
Author: Richard Brent
Keywords: Docker,balance,mydomuk
Classifier: License :: Free For Home Use
Classifier: Programming Language :: Python
Requires-Python: >=3.7
Requires-Dist: python-dotenv >=1.0.0
Requires-Dist: certifi >=2023.5.7
Requires-Dist: charset-normalizer >=3.2.0
Requires-Dist: docker >=6.1.3
Requires-Dist: idna >=3.4
Requires-Dist: packaging >=23.1
Requires-Dist: PyYAML >=6.0.1
Requires-Dist: requests >=2.31.0
Requires-Dist: urllib3 >=2.0.3
Requires-Dist: wheel >=0.42.0
Requires-Dist: websocket-client >=1.6.1
